linkgo/__init__.py
linkgo/linkgo.py
linkgo-0.1.4.dist-info/licenses/LICENSE
linkgo-0.1.4.dist-info/METADATA
linkgo-0.1.4.dist-info/WHEEL
linkgo-0.1.4.dist-info/entry_points.txt
linkgo-0.1.4.dist-info/top_level.txt
linkgo-0.1.4.dist-info/RECORD
