Metadata-Version: 2.4
Name: linkgo
Version: 0.1.4
Summary: An extremely fast, professional-grade tool to find and extract all hyperlinks from web pages based on a search query.
Author-email: ghoste12125 <anonymosmauros@gmail.com>
License: MIT License
Project-URL: Homepage, https://github.com/ghostescript/linkgo
Project-URL: Bug Tracker, https://github.com/ghostescript/linkgo/issues
Classifier: Programming Language :: Python :: 3
Classifier: License :: OSI Approved :: MIT License
Classifier: Operating System :: OS Independent
Classifier: Topic :: Internet :: WWW/HTTP
Classifier: Topic :: Utilities
Requires-Python: >=3.7
License-File: LICENSE
Requires-Dist: ddgs
Requires-Dist: aiohttp
Requires-Dist: beautifulsoup4
Dynamic: license-file
